PyLongQt/Qt5Core.dll
PyLongQt/_PyLongQt.cp39-win_amd64.pyd
PyLongQt/__init__.py
PyLongQt/_converters.py
PyLongQt/_grid.py
PyLongQt/_runsim.py
PyLongQt/translations/qt_ar.qm
PyLongQt/translations/qt_bg.qm
PyLongQt/translations/qt_ca.qm
PyLongQt/translations/qt_cs.qm
PyLongQt/translations/qt_da.qm
PyLongQt/translations/qt_de.qm
PyLongQt/translations/qt_en.qm
PyLongQt/translations/qt_es.qm
PyLongQt/translations/qt_fi.qm
PyLongQt/translations/qt_fr.qm
PyLongQt/translations/qt_gd.qm
PyLongQt/translations/qt_he.qm
PyLongQt/translations/qt_hu.qm
PyLongQt/translations/qt_it.qm
PyLongQt/translations/qt_ja.qm
PyLongQt/translations/qt_ko.qm
PyLongQt/translations/qt_lv.qm
PyLongQt/translations/qt_pl.qm
PyLongQt/translations/qt_ru.qm
PyLongQt/translations/qt_sk.qm
PyLongQt/translations/qt_tr.qm
PyLongQt/translations/qt_uk.qm
PyLongQt/translations/qt_zh_TW.qm
hundlab_PyLongQt-0.5.dist-info/LICENSE
hundlab_PyLongQt-0.5.dist-info/METADATA
hundlab_PyLongQt-0.5.dist-info/WHEEL
hundlab_PyLongQt-0.5.dist-info/top_level.txt
hundlab_PyLongQt-0.5.dist-info/RECORD
