Metadata-Version: 2.1
Name: hundlab-PyLongQt
Version: 0.5
Summary: Python bindings for LongQt
Home-page: https://github.com/hundlab/PyLongQt
Author: Thomas Hund
Author-email: hund.1@osu.edu
License: GNU GPL v3.0
Project-URL: Documentation, https://hundlab.github.io/PyLongQt
Platform: UNKNOWN
License-File: LICENSE
Requires-Dist: PyQt5
Requires-Dist: numpy
Requires-Dist: pandas
